ylz_langchain/__init__.py
ylz_langchain/cli/__init__.py
ylz_langchain/cli/chat.py
ylz_langchain/cli/custom_service/__init__.py
ylz_langchain/cli/custom_service/car_rentals.py
ylz_langchain/cli/custom_service/db_init.py
ylz_langchain/cli/custom_service/excursions.py
ylz_langchain/cli/custom_service/flights.py
ylz_langchain/cli/custom_service/graph.py
ylz_langchain/cli/custom_service/hotels.py
ylz_langchain/cli/custom_service/policies.py
ylz_langchain/cli/custom_service/utils.py
ylz_langchain/cli/graph.py
ylz_langchain/cli/hooks.py
ylz_langchain/cli/init.py
ylz_langchain/cli/main.py
ylz_langchain/cli/neo4j.py
ylz_langchain/cli/rag.py
ylz_langchain/cli/reset.py
ylz_langchain/cli/serve.py
ylz_langchain/cli/start.py
ylz_langchain/cli/test.py
ylz_langchain/config.yaml
ylz_langchain/langchain/__init__.py
ylz_langchain/langchain/agents/__init__.py
ylz_langchain/langchain/documents/__init__.py
ylz_langchain/langchain/documents/dir_loader.py
ylz_langchain/langchain/documents/docx.py
ylz_langchain/langchain/documents/image.py
ylz_langchain/langchain/documents/pdf.py
ylz_langchain/langchain/documents/pptx.py
ylz_langchain/langchain/documents/url.py
ylz_langchain/langchain/embeddings/__init__.py
ylz_langchain/langchain/flux/__init__.py
ylz_langchain/langchain/graph/__init__.py
ylz_langchain/langchain/graph/db_graph/__init__.py
ylz_langchain/langchain/graph/engineer_graph/__init__.py
ylz_langchain/langchain/graph/engineer_graph/check.py
ylz_langchain/langchain/graph/engineer_graph/critique.py
ylz_langchain/langchain/graph/engineer_graph/draft.py
ylz_langchain/langchain/graph/engineer_graph/gather_requirements.py
ylz_langchain/langchain/graph/engineer_graph/llm.py
ylz_langchain/langchain/graph/engineer_graph/loader.py
ylz_langchain/langchain/graph/engineer_graph/state.py
ylz_langchain/langchain/graph/life_graph/__init__.py
ylz_langchain/langchain/graph/life_graph/agent_node.py
ylz_langchain/langchain/graph/life_graph/life_node.py
ylz_langchain-0.1.0.dist-info/METADATA
ylz_langchain-0.1.0.dist-info/WHEEL
ylz_langchain-0.1.0.dist-info/RECORD
