Metadata-Version: 2.1
Name: ylz-langchain
Version: 0.1.0
Summary: 
Author: Your Name
Author-email: you@example.com
Requires-Python: >=3.12,<4.0
Classifier: Programming Language :: Python :: 3
Classifier: Programming Language :: Python :: 3.12
Classifier: Programming Language :: Python :: 3.13
Requires-Dist: aiosqlite (>=0.20.0,<0.21.0)
Requires-Dist: akshare (>=1.15.22,<2.0.0)
Requires-Dist: annotated-types (>=0.7.0,<0.8.0)
Requires-Dist: apscheduler (>=3.10.4,<4.0.0)
Requires-Dist: argparse (>=1.4.0,<2.0.0)
Requires-Dist: bilibili-api-python (>=17.1.1,<18.0.0)
Requires-Dist: cryptography (>=44.0.0,<45.0.0)
Requires-Dist: dashscope (>=1.20.4,<2.0.0)
Requires-Dist: distro (>=1.9.0,<2.0.0)
Requires-Dist: docx2txt (>=0.8,<0.9)
Requires-Dist: duckduckgo-search (>=6.2.1,<7.0.0)
Requires-Dist: elastic-transport (>=8.15.0,<9.0.0)
Requires-Dist: elasticsearch-dsl (>=8.15.2,<9.0.0)
Requires-Dist: faiss-cpu (>=1.10.0,<2.0.0)
Requires-Dist: fastapi (>=0.111.1,<0.112.0)
Requires-Dist: fastapi-cdn-host (>=0.8.2,<0.9.0)
Requires-Dist: google-search-results (>=2.4.2,<3.0.0)
Requires-Dist: gradio-client (>=1.1.1,<2.0.0)
Requires-Dist: gradio-tools (>=0.0.9,<0.0.10)
Requires-Dist: grandalf (>=0.8,<0.9)
Requires-Dist: h11 (>=0.14.0,<0.15.0)
Requires-Dist: ipfs-toolkit (>=0.5.24,<0.6.0)
Requires-Dist: jieba (>=0.42.1,<0.43.0)
Requires-Dist: jionlp (>=1.5.15,<2.0.0)
Requires-Dist: langchain (>=0.3.0,<0.4.0)
Requires-Dist: langchain-community
Requires-Dist: langchain-elasticsearch
Requires-Dist: langchain-experimental
Requires-Dist: langchain-ollama
Requires-Dist: langchain-openai
Requires-Dist: langchain-together
Requires-Dist: langgraph (>=0.2.28,<0.3.0)
Requires-Dist: langgraph-checkpoint (==1.0.9)
Requires-Dist: langgraph-cli (>=0.1.52,<0.2.0)
Requires-Dist: langserve
Requires-Dist: markdownify (>=0.13.1,<0.14.0)
Requires-Dist: matplotlib (>=3.9.0,<4.0.0)
Requires-Dist: mpmath (>=1.3.0,<2.0.0)
Requires-Dist: neo4j (>=5.23.1,<6.0.0)
Requires-Dist: numpy (<2)
Requires-Dist: opentelemetry-sdk (>=1.27.0,<2.0.0)
Requires-Dist: pdfminer (>=20191125,<20191126)
Requires-Dist: pdfplumber (>=0.11.2,<0.12.0)
Requires-Dist: pillow-heif (>=0.18.0,<0.19.0)
Requires-Dist: playwright (>=1.45.1,<2.0.0)
Requires-Dist: pydantic-core (>=2.20.1,<3.0.0)
Requires-Dist: python-docx (>=1.1.2,<2.0.0)
Requires-Dist: python-dotenv (>=1.0.1,<2.0.0)
Requires-Dist: python-pptx (>=0.6.23,<0.7.0)
Requires-Dist: pyyaml (>=6.0.1,<7.0.0)
Requires-Dist: qianfan (>=0.4.2,<0.5.0)
Requires-Dist: requests (>=2.32.3,<3.0.0)
Requires-Dist: rich (>=13.8.1,<14.0.0)
Requires-Dist: scikit-learn (>=1.6.1,<2.0.0)
Requires-Dist: serpapi (>=0.1.5,<0.2.0)
Requires-Dist: sqlite4 (>=0.1.1,<0.2.0)
Requires-Dist: sse-starlette (>=2.1.2,<3.0.0)
Requires-Dist: tabulate (>=0.9.0,<0.10.0)
Requires-Dist: torch (==2.2.1)
Requires-Dist: trustcall (>=0.0.22,<0.0.23)
Requires-Dist: typing-extensions (>=4.12.2,<5.0.0)
Requires-Dist: websockets (==11.0)
Requires-Dist: wolframalpha (>=5.1.3,<6.0.0)
